df_style.css
pyreport2to3/__init__.py
pyreport2to3/pyreport2to3.py
pyreport2to3-1.2.2.dist-info/LICENSE
pyreport2to3-1.2.2.dist-info/METADATA
pyreport2to3-1.2.2.dist-info/WHEEL
pyreport2to3-1.2.2.dist-info/top_level.txt
pyreport2to3-1.2.2.dist-info/RECORD
