Metadata-Version: 2.1
Name: pyreport2to3
Version: 1.2.2
Summary: Python 2 to 3 porting HTML report 
Home-page: https://github.com/catchmaurya/pyreport2to3
Author: Maurya Allimuthu
Author-email: catchmaurya@gmail.com
License: UNKNOWN
Platform: UNKNOWN
Classifier: Programming Language :: Python :: 2.7
Classifier: Programming Language :: Python :: 3
Classifier: License :: OSI Approved :: MIT License
Classifier: Operating System :: OS Independent
Requires-Dist: 2to3 (>=1.0)
Requires-Dist: future (>=0.18.2)
Requires-Dist: Jinja2 (>=2.11.2)
Requires-Dist: matplotlib (>=2.2.5)
Requires-Dist: modernize (>=0.7)
Requires-Dist: numpy (>=0.7)
Requires-Dist: pandas (>=0.24.2)
